iagro_sdk/__init__.py
iagro_sdk/exceptions.py
iagro_sdk/model.py
iagro_sdk/repository.py
iagro_sdk/schemas.py
iagro_sdk-0.3.1.dist-info/METADATA
iagro_sdk-0.3.1.dist-info/WHEEL
iagro_sdk-0.3.1.dist-info/RECORD
