Metadata-Version: 2.3
Name: iagro-sdk
Version: 0.3.1
Summary: Pacote de códigos que serão reutilizados nnos projetos da IAgro
Author: armandoluz
Author-email: armandoari.288@gmail.com
Requires-Python: >=3.12
Classifier: Programming Language :: Python :: 3
Classifier: Programming Language :: Python :: 3.12
Classifier: Programming Language :: Python :: 3.13
Requires-Dist: pydantic (>=2.11.9,<3.0.0)
Requires-Dist: sqlalchemy (>=2.0.43,<3.0.0)
Requires-Dist: sqlmodel (>=0.0.24,<0.0.25)
